YoMoPie/YoMoPie.py
YoMoPie/__init__.py
YoMoPie/lib_nrf24.py
YoMoPie-0.4.dist-info/DESCRIPTION.rst
YoMoPie-0.4.dist-info/METADATA
YoMoPie-0.4.dist-info/RECORD
YoMoPie-0.4.dist-info/WHEEL
YoMoPie-0.4.dist-info/metadata.json
YoMoPie-0.4.dist-info/top_level.txt
