Metadata-Version: 2.0
Name: YoMoPie
Version: 0.4
Summary: YoMoPie Library
Home-page: https://github.com/klemenjak/YoMoPie
Author: S. Jost
Author-email: stefan.jost@aau.at
License: Apache2
Platform: UNKNOWN
Classifier: Development Status :: 4 - Beta
Classifier: Intended Audience :: Developers
Classifier: Programming Language :: Python :: 3
Requires-Dist: RPi.GPIO
Requires-Dist: spidev
